MANIFEST.in
NEWS.txt
README.txt
setup.cfg
setup.py
src/pyroutes.js.egg-info/PKG-INFO
src/pyroutes.js.egg-info/SOURCES.txt
src/pyroutes.js.egg-info/dependency_links.txt
src/pyroutes.js.egg-info/not-zip-safe
src/pyroutes.js.egg-info/requires.txt
src/pyroutes.js.egg-info/top_level.txt
src/pyroutesjs/__init__.py
src/pyroutesjs/pyroutes.js