Metadata-Version: 1.0
Name: pyroutes.js
Version: 0.1.0
Summary: PyRoutesJS provide a Javascript routes generation function like Python Routes Mapper.generate method
Home-page: http://pypi.python.org/pypi/pyroutes.js/
Author: Stephane Klein
Author-email: stephane@harobed.org
License: BSD
Platform: UNKNOWN
